{
  "BakeInfoLayouts": [
    {
      "UniqueName": "SubMission_802720601",
      "TypeId": "TypeId_SubMissionInfoConfig",
      "Offset": 2
    },
    {
      "UniqueName": "SubMission_802720602",
      "TypeId": "TypeId_SubMissionInfoConfig",
      "Offset": 89
    },
    {
      "UniqueName": "SubMission_802720603",
      "TypeId": "TypeId_SubMissionInfoConfig",
      "Offset": 240
    },
    {
      "UniqueName": "SubMission_802720604",
      "TypeId": "TypeId_SubMissionInfoConfig",
      "Offset": 391
    },
    {
      "UniqueName": "SubMission_802720605",
      "TypeId": "TypeId_SubMissionInfoConfig",
      "Offset": 508
    },
    {
      "UniqueName": "SubMission_802720606",
      "TypeId": "TypeId_SubMissionInfoConfig",
      "Offset": 600
    },
    {
      "UniqueName": "SubMission_802720607",
      "TypeId": "TypeId_SubMissionInfoConfig",
      "Offset": 676
    },
    {
      "UniqueName": "SubMission_802720608",
      "TypeId": "TypeId_SubMissionInfoConfig",
      "Offset": 809
    }
  ]
}