{
  "BakeInfoLayouts": [
    {
      "UniqueName": "Monster_W1_SvarogPart_00_CountDown",
      "Offset": 8736
    },
    {
      "UniqueName": "Monster_W1_SvarogPart_00_Overload",
      "Offset": 8887
    },
    {
      "UniqueName": "Monster_W1_SvarogPart_00_CD",
      "Offset": 8916
    },
    {
      "UniqueName": "Monster_W1_GS_Svarog_DisableAction",
      "Offset": 8957
    },
    {
      "UniqueName": "Monster_W1_GS_Svarog_Level_SpecialWin",
      "Offset": 9000
    },
    {
      "UniqueName": "Svarog_Control_Modifier",
      "Offset": 9054
    },
    {
      "UniqueName": "Svarog_Electric_Modifier",
      "Offset": 9831
    },
    {
      "UniqueName": "M_Svarog_CTRL",
      "Offset": 9978,
      "Dependency": [
        "Stun_Effect"
      ]
    },
    {
      "UniqueName": "Svarog_Skill06_Insert_Modifier",
      "Offset": 10414
    },
    {
      "UniqueName": "Svarog_Part_ListenHP_Modifier",
      "Offset": 10496
    },
    {
      "UniqueName": "Svarog_Kaboom_Modifier",
      "Offset": 10758
    },
    {
      "UniqueName": "Svarog_Part0_DamageReduceModifier",
      "Offset": 10906
    },
    {
      "UniqueName": "Svarog_Skill06_Buff",
      "Offset": 11078
    },
    {
      "UniqueName": "Svarog_ListenPlayerDie_Modifier",
      "Offset": 11233
    },
    {
      "UniqueName": "Svarog_Part_OnTurnEndChangePhaseModifier",
      "Offset": 11986
    },
    {
      "UniqueName": "Svarog_Part_ListenBreak_Modifier",
      "Offset": 12157
    },
    {
      "UniqueName": "Svarog_Skill07_AllDamageUp_Modifier",
      "Offset": 12499
    },
    {
      "UniqueName": "Svarog_Control_OnPart_Modifier",
      "Offset": 12559
    },
    {
      "UniqueName": "Monster_Svarog_00_Unselectable",
      "TypeId": "TypeId_TargetAliasConfig",
      "Offset": 13314
    },
    {
      "UniqueName": "Monster_W1_Svarog_00_PassiveSkill_BGM",
      "TypeId": "TypeId_TurnBasedAbilityConfig",
      "Offset": 2
    },
    {
      "UniqueName": "Monster_W1_GS_Svarog_PassiveSkillInitiate",
      "TypeId": "TypeId_TurnBasedAbilityConfig",
      "Offset": 380
    },
    {
      "UniqueName": "Monster_W1_GS_Svarog_Skill01_Phase01",
      "TypeId": "TypeId_TurnBasedAbilityConfig",
      "Offset": 948
    },
    {
      "UniqueName": "Monster_W1_GS_Svarog_Skill01_Phase02",
      "TypeId": "TypeId_TurnBasedAbilityConfig",
      "Offset": 1212
    },
    {
      "UniqueName": "Monster_W1_GS_Svarog_Skill02_Phase01",
      "TypeId": "TypeId_TurnBasedAbilityConfig",
      "Offset": 1546
    },
    {
      "UniqueName": "Monster_W1_GS_Svarog_Skill02_Phase02",
      "TypeId": "TypeId_TurnBasedAbilityConfig",
      "Offset": 1837
    },
    {
      "UniqueName": "Monster_W1_GS_Svarog_Skill03_Phase01",
      "TypeId": "TypeId_TurnBasedAbilityConfig",
      "Offset": 2180
    },
    {
      "UniqueName": "Monster_W1_GS_Svarog_Skill03_Phase02",
      "TypeId": "TypeId_TurnBasedAbilityConfig",
      "Offset": 2647
    },
    {
      "UniqueName": "Monster_W1_GS_Svarog_Skill04_Phase01",
      "TypeId": "TypeId_TurnBasedAbilityConfig",
      "Offset": 4444
    },
    {
      "UniqueName": "Monster_W1_GS_Svarog_Skill04_Phase02",
      "TypeId": "TypeId_TurnBasedAbilityConfig",
      "Offset": 4899
    },
    {
      "UniqueName": "Monster_W1_GS_Svarog_Skill05_Phase01",
      "TypeId": "TypeId_TurnBasedAbilityConfig",
      "Offset": 5675
    },
    {
      "UniqueName": "Monster_W1_GS_Svarog_Skill05_Phase02",
      "TypeId": "TypeId_TurnBasedAbilityConfig",
      "Offset": 6103
    },
    {
      "UniqueName": "Monster_W1_GS_Svarog_Skill06_Phase01",
      "TypeId": "TypeId_TurnBasedAbilityConfig",
      "Offset": 6440
    },
    {
      "UniqueName": "Monster_W1_GS_Svarog_Skill06_Phase02",
      "TypeId": "TypeId_TurnBasedAbilityConfig",
      "Offset": 6937
    },
    {
      "UniqueName": "Monster_W1_GS_Svarog_Skill07_Phase01",
      "TypeId": "TypeId_TurnBasedAbilityConfig",
      "Offset": 7075
    },
    {
      "UniqueName": "Monster_W1_GS_Svarog_Skill07_Phase02",
      "TypeId": "TypeId_TurnBasedAbilityConfig",
      "Offset": 7284
    },
    {
      "UniqueName": "Monster_W1_GS_Svarog_AIControl",
      "TypeId": "TypeId_TurnBasedAbilityConfig",
      "Offset": 7720
    },
    {
      "UniqueName": "Monster_W1_GS_Svarog_Skill08_Phase01",
      "TypeId": "TypeId_TurnBasedAbilityConfig",
      "Offset": 7955
    },
    {
      "UniqueName": "Monster_W1_GS_Svarog_Skill08_Phase02",
      "TypeId": "TypeId_TurnBasedAbilityConfig",
      "Offset": 8124
    },
    {
      "UniqueName": "Monster_W1_GS_Svarog_PassiveSkill03",
      "TypeId": "TypeId_TurnBasedAbilityConfig",
      "Offset": 8291
    },
    {
      "UniqueName": "Monster_W1_GS_Svarog_PassiveSkill02",
      "TypeId": "TypeId_TurnBasedAbilityConfig",
      "Offset": 8457
    },
    {
      "UniqueName": "Monster_W1_GS_Svarog_PassiveSkill04",
      "TypeId": "TypeId_TurnBasedAbilityConfig",
      "Offset": 8499
    }
  ]
}