{
  "$type": "RPG.GameCore.RtLevelGroupInfo",
  "GroupName": "RogueModule_Tournament_Content_NPCExtra",
  "Category": "Custom",
  "AreaAnchorName": "LevelArea_P80703_F80703001_G96",
  "LoadSide": "Server",
  "LoadOnInitial": true,
  "ValueSource": {},
  "ConflictIDList": [],
  "IsHoyoGroup": true,
  "ConflictWhiteList": [],
  "AnchorList": [],
  "MonsterList": [],
  "PropList": [],
  "DistrictList": [],
  "WaypointList": [],
  "PathwayList": [],
  "BattleAreaList": [],
  "NPCList": [
    {
      "NPCID": 3013,
      "LevelGraph": "Config/Level/Maze/MazeRogue/Maze_Rogue_NPC_EventPainting.json",
      "ValueSource": {},
      "StaticNPC": true,
      "DialogueGroups": [],
      "ServerInteractVerificationIDList": [],
      "BoardShowList": [],
      "TalkDialogGroupIDList": [],
      "DefaultAnimationType": "IdleState",
      "AdditiveResidentEffect": [],
      "InitialHiddenNodeList": [],
      "DialogueTriggerSkipSpecifiedFakeAvatarList": [],
      "OverrideReplaceMaterialKeyList": [],
      "CameraCenterEntityList": [],
      "CameraConfig": {},
      "SpawnConfig": {
        "EntitySpawnConfig": {}
      },
      "ModelPresetConfig": {},
      "TriggerValidGuest": {},
      "TagOverrideConfig": {
        "Mode": "Merge",
        "OverrideTags": {},
        "AdditiveTags": {
          "List": [
            {
              "Tag": "Rogue.NPC.Event",
              "TagHash": 1332388031
            }
          ]
        },
        "SubtractiveTags": {}
      },
      "Name": "NPC1",
      "RotY": 308.3923,
      "ID": 400001,
      "PosX": 35.99,
      "PosY": 36.68,
      "PosZ": -62.97001
    },
    {
      "NPCID": 3013,
      "LevelGraph": "Config/Level/Maze/MazeRogue/Maze_Rogue_NPC_EventPainting.json",
      "ValueSource": {},
      "StaticNPC": true,
      "DialogueGroups": [],
      "ServerInteractVerificationIDList": [],
      "BoardShowList": [],
      "TalkDialogGroupIDList": [],
      "DefaultAnimationType": "IdleState",
      "AdditiveResidentEffect": [],
      "InitialHiddenNodeList": [],
      "DialogueTriggerSkipSpecifiedFakeAvatarList": [],
      "OverrideReplaceMaterialKeyList": [],
      "CameraCenterEntityList": [],
      "CameraConfig": {},
      "SpawnConfig": {
        "EntitySpawnConfig": {}
      },
      "ModelPresetConfig": {},
      "TriggerValidGuest": {},
      "TagOverrideConfig": {
        "Mode": "Merge",
        "OverrideTags": {},
        "AdditiveTags": {
          "List": [
            {
              "Tag": "Rogue.NPC.Event",
              "TagHash": 1332388031
            }
          ]
        },
        "SubtractiveTags": {}
      },
      "Name": "NPC2",
      "RotY": 308.3923,
      "ID": 400002,
      "PosX": 32.26375,
      "PosY": 36.68,
      "PosZ": -67.67262
    }
  ],
  "CrowdList": [],
  "PedestrianList": [],
  "PedestrianV2List": [],
  "AudienceList": [],
  "SmartObjectList": [],
  "CurveList": [],
  "LittleGameList": []
}