{
  "OnInitSequece": [],
  "OnStartSequece": [
    {
      "TaskList": [
        {
          "$type": "RPG.GameCore.TriggerPerformance",
          "PerformanceType": "PlayVideo",
          "PerformanceID": 103380522,
          "MaskConfig": {
            "UseExcelData": false,
            "StartBlack": "NoPre",
            "EndBlack": "NoPost"
          },
          "ValueSource": {}
        },
        {
          "$type": "RPG.GameCore.ClientFinishMission",
          "SubmissionID": 103380513
        }
      ]
    }
  ],
  "Type": "Group"
}