{
  "BakeInfoLayouts": [
    {
      "UniqueName": "StageAbility_VS_BE_BaseSpeed_Modifier",
      "Offset": 81526
    },
    {
      "UniqueName": "StageAbility_VS_BE_ExtraSpeed_Modifier",
      "Offset": 81627
    },
    {
      "UniqueName": "StageAbility_VS_Weapon_009_PLY_Permanent_Modifier",
      "Offset": 81737
    },
    {
      "UniqueName": "StageAbility_VS_Weapon_012_BOSS_Modifier",
      "Offset": 81871
    },
    {
      "UniqueName": "StageAbility_VS_Weapon_006_PLY_Shield_Mark_Modifier",
      "Offset": 82537
    },
    {
      "UniqueName": "StageAbility_VS_Commnon_MuteLevelUp",
      "Offset": 82574
    },
    {
      "UniqueName": "StageAbility_VS_Commnon_MuteLevelUpMark",
      "Offset": 82626
    },
    {
      "UniqueName": "StageAbility_VS_Weapon_007_PLY_Modifier",
      "Offset": 82671
    },
    {
      "UniqueName": "VS_LE_AbilityInit",
      "TypeId": "TypeId_TaskListTemplateConfig",
      "Offset": 82698
    },
    {
      "UniqueName": "VS_VAR_LevelWeaponAttack",
      "TypeId": "TypeId_TaskListTemplateConfig",
      "Offset": 82758
    },
    {
      "UniqueName": "VS_Weapon_SpecialAction",
      "TypeId": "TypeId_TaskListTemplateConfig",
      "Offset": 82840
    },
    {
      "UniqueName": "VS_Weapon_SwitchBEIcon",
      "TypeId": "TypeId_TaskListTemplateConfig",
      "Offset": 86638
    },
    {
      "UniqueName": "StageAbility_VS_Weapon_001",
      "TypeId": "TypeId_TurnBasedAbilityConfig",
      "Offset": 2
    },
    {
      "UniqueName": "StageAbility_VS_Weapon_002",
      "TypeId": "TypeId_TurnBasedAbilityConfig",
      "Offset": 3969
    },
    {
      "UniqueName": "StageAbility_VS_Weapon_002_Insert",
      "TypeId": "TypeId_TurnBasedAbilityConfig",
      "Offset": 5082
    },
    {
      "UniqueName": "StageAbility_VS_Weapon_003",
      "TypeId": "TypeId_TurnBasedAbilityConfig",
      "Offset": 10691
    },
    {
      "UniqueName": "StageAbility_VS_Weapon_003_Insert",
      "TypeId": "TypeId_TurnBasedAbilityConfig",
      "Offset": 11402
    },
    {
      "UniqueName": "StageAbility_VS_Weapon_004",
      "TypeId": "TypeId_TurnBasedAbilityConfig",
      "Offset": 14431
    },
    {
      "UniqueName": "StageAbility_VS_Weapon_004_Insert",
      "TypeId": "TypeId_TurnBasedAbilityConfig",
      "Offset": 20123
    },
    {
      "UniqueName": "StageAbility_VS_Weapon_005",
      "TypeId": "TypeId_TurnBasedAbilityConfig",
      "Offset": 22905
    },
    {
      "UniqueName": "StageAbility_VS_Weapon_005_Insert",
      "TypeId": "TypeId_TurnBasedAbilityConfig",
      "Offset": 23888
    },
    {
      "UniqueName": "StageAbility_VS_Weapon_006",
      "TypeId": "TypeId_TurnBasedAbilityConfig",
      "Offset": 26654
    },
    {
      "UniqueName": "StageAbility_VS_Weapon_007",
      "TypeId": "TypeId_TurnBasedAbilityConfig",
      "Offset": 34368
    },
    {
      "UniqueName": "StageAbility_VS_Weapon_007_Insert",
      "TypeId": "TypeId_TurnBasedAbilityConfig",
      "Offset": 37750
    },
    {
      "UniqueName": "StageAbility_VS_Weapon_008",
      "TypeId": "TypeId_TurnBasedAbilityConfig",
      "Offset": 43413
    },
    {
      "UniqueName": "StageAbility_VS_Weapon_008_Insert",
      "TypeId": "TypeId_TurnBasedAbilityConfig",
      "Offset": 44448
    },
    {
      "UniqueName": "StageAbility_VS_Weapon_009",
      "TypeId": "TypeId_TurnBasedAbilityConfig",
      "Offset": 56553
    },
    {
      "UniqueName": "StageAbility_VS_Weapon_009_Insert",
      "TypeId": "TypeId_TurnBasedAbilityConfig",
      "Offset": 58235
    },
    {
      "UniqueName": "StageAbility_VS_Weapon_010",
      "TypeId": "TypeId_TurnBasedAbilityConfig",
      "Offset": 60484
    },
    {
      "UniqueName": "StageAbility_VS_Weapon_010_Insert",
      "TypeId": "TypeId_TurnBasedAbilityConfig",
      "Offset": 61708
    },
    {
      "UniqueName": "StageAbility_VS_Weapon_011",
      "TypeId": "TypeId_TurnBasedAbilityConfig",
      "Offset": 64641
    },
    {
      "UniqueName": "StageAbility_VS_Weapon_011_Insert",
      "TypeId": "TypeId_TurnBasedAbilityConfig",
      "Offset": 66310
    },
    {
      "UniqueName": "StageAbility_VS_Weapon_012",
      "TypeId": "TypeId_TurnBasedAbilityConfig",
      "Offset": 70955
    },
    {
      "UniqueName": "StageAbility_VS_Weapon_012_Insert",
      "TypeId": "TypeId_TurnBasedAbilityConfig",
      "Offset": 72965
    },
    {
      "UniqueName": "StageAbility_VS_Weapon_013",
      "TypeId": "TypeId_TurnBasedAbilityConfig",
      "Offset": 74645
    },
    {
      "UniqueName": "StageAbility_VS_Weapon_013_Insert",
      "TypeId": "TypeId_TurnBasedAbilityConfig",
      "Offset": 76228
    }
  ]
}