{
  "RegionList": [
    {
      "RegionID": 3,
      "ConnectivityList": [
        {
          "FromRegionID": 3,
          "ToRegionID": 4,
          "HasConnectWayPoint": true,
          "ConnectPointKey": "Connect_8",
          "ConditionInfos": {
            "Conditions": []
          }
        },
        {
          "FromRegionID": 3,
          "ToRegionID": 6,
          "HasConnectWayPoint": true,
          "ConnectPointKey": "Connect_3",
          "ConditionInfos": {
            "Conditions": []
          }
        },
        {
          "FromRegionID": 3,
          "ToRegionID": 10,
          "HasConnectWayPoint": true,
          "ConnectPointKey": "Connect_7",
          "ConnectionType": "Teleport",
          "Destination": "Connect_7B",
          "ConditionInfos": {
            "Conditions": []
          }
        },
        {
          "FromRegionID": 3,
          "ToRegionID": 7,
          "HasConnectWayPoint": true,
          "ConnectPointKey": "Connect_4",
          "ConnectionType": "Teleport",
          "Destination": "Connect_4B",
          "ConditionInfos": {
            "Conditions": []
          }
        },
        {
          "FromRegionID": 3,
          "ToRegionID": 8,
          "HasConnectWayPoint": true,
          "ConnectPointKey": "Connect_6B",
          "ConnectionType": "Teleport",
          "Destination": "Connect_6",
          "ConditionInfos": {
            "Conditions": []
          }
        }
      ],
      "StateConfigList": [
        {
          "StateID": 1,
          "Condition": {
            "Conditions": [
              {
                "$type": "RPG.GameCore.LevelRegionStateSavedValueCondition",
                "SavedValueName": "FSV_LightStateByMainMission"
              },
              {
                "$type": "RPG.GameCore.LevelRegionStateCustomValueCondition",
                "CustomValueName": "FCV_LightState"
              }
            ]
          }
        },
        {
          "StateID": 2,
          "Condition": {
            "Conditions": [
              {
                "$type": "RPG.GameCore.LevelRegionStateSavedValueCondition",
                "SavedValueName": "FSV_LightStateByMainMission",
                "Value": 1
              },
              {
                "$type": "RPG.GameCore.LevelRegionStateCustomValueCondition",
                "CustomValueName": "FCV_LightState",
                "Value": 1
              }
            ],
            "Operation": "Or"
          }
        }
      ]
    },
    {
      "RegionID": 7,
      "ConnectivityList": [
        {
          "FromRegionID": 7,
          "ToRegionID": 3,
          "HasConnectWayPoint": true,
          "ConnectPointKey": "Connect_4B",
          "ConnectionType": "Teleport",
          "Destination": "Connect_4",
          "ConditionInfos": {
            "Conditions": []
          }
        },
        {
          "FromRegionID": 7,
          "ToRegionID": 8,
          "HasConnectWayPoint": true,
          "ConnectPointKey": "Connect_5",
          "ConnectionType": "Teleport",
          "Destination": "Connect_5B",
          "ConditionInfos": {
            "Conditions": []
          }
        }
      ],
      "StateConfigList": [
        {
          "StateID": 1,
          "Condition": {
            "Conditions": [
              {
                "$type": "RPG.GameCore.LevelRegionStateSavedValueCondition",
                "SavedValueName": "FSV_LightStateByMainMission"
              },
              {
                "$type": "RPG.GameCore.LevelRegionStateCustomValueCondition",
                "CustomValueName": "FCV_LightState"
              }
            ]
          }
        },
        {
          "StateID": 2,
          "Condition": {
            "Conditions": [
              {
                "$type": "RPG.GameCore.LevelRegionStateSavedValueCondition",
                "SavedValueName": "FSV_LightStateByMainMission",
                "Value": 1
              },
              {
                "$type": "RPG.GameCore.LevelRegionStateCustomValueCondition",
                "CustomValueName": "FCV_LightState",
                "Value": 1
              }
            ],
            "Operation": "Or"
          }
        }
      ]
    },
    {
      "RegionID": 8,
      "ConnectivityList": [
        {
          "FromRegionID": 8,
          "ToRegionID": 3,
          "HasConnectWayPoint": true,
          "ConnectPointKey": "Connect_6",
          "ConnectionType": "Teleport",
          "Destination": "Connect_6B",
          "ConditionInfos": {
            "Conditions": []
          }
        },
        {
          "FromRegionID": 8,
          "ToRegionID": 7,
          "HasConnectWayPoint": true,
          "ConnectPointKey": "Connect_5B",
          "ConnectionType": "Teleport",
          "Destination": "Connect_5",
          "ConditionInfos": {
            "Conditions": []
          }
        }
      ],
      "StateConfigList": [
        {
          "StateID": 1,
          "Condition": {
            "Conditions": [
              {
                "$type": "RPG.GameCore.LevelRegionStateSavedValueCondition",
                "SavedValueName": "FSV_LightStateByMainMission"
              },
              {
                "$type": "RPG.GameCore.LevelRegionStateCustomValueCondition",
                "CustomValueName": "FCV_LightState"
              }
            ]
          }
        },
        {
          "StateID": 2,
          "Condition": {
            "Conditions": [
              {
                "$type": "RPG.GameCore.LevelRegionStateSavedValueCondition",
                "SavedValueName": "FSV_LightStateByMainMission",
                "Value": 1
              },
              {
                "$type": "RPG.GameCore.LevelRegionStateCustomValueCondition",
                "CustomValueName": "FCV_LightState",
                "Value": 1
              }
            ],
            "Operation": "Or"
          }
        }
      ]
    },
    {
      "RegionID": 10,
      "ConnectivityList": [
        {
          "FromRegionID": 10,
          "ToRegionID": 3,
          "HasConnectWayPoint": true,
          "ConnectPointKey": "Connect_7B",
          "ConnectionType": "Teleport",
          "Destination": "Connect_7",
          "ConditionInfos": {
            "Conditions": []
          }
        }
      ],
      "StateConfigList": [
        {
          "StateID": 1,
          "Condition": {
            "Conditions": [
              {
                "$type": "RPG.GameCore.LevelRegionStateSavedValueCondition",
                "SavedValueName": "FSV_LightStateByMainMission"
              },
              {
                "$type": "RPG.GameCore.LevelRegionStateCustomValueCondition",
                "CustomValueName": "FCV_LightState"
              }
            ]
          }
        },
        {
          "StateID": 2,
          "Condition": {
            "Conditions": [
              {
                "$type": "RPG.GameCore.LevelRegionStateSavedValueCondition",
                "SavedValueName": "FSV_LightStateByMainMission",
                "Value": 1
              },
              {
                "$type": "RPG.GameCore.LevelRegionStateCustomValueCondition",
                "CustomValueName": "FCV_LightState",
                "Value": 1
              }
            ],
            "Operation": "Or"
          }
        }
      ]
    },
    {
      "RegionID": 5,
      "ConnectivityList": [
        {
          "FromRegionID": 5,
          "ToRegionID": 1,
          "HasConnectWayPoint": true,
          "ConnectPointKey": "Connect_1",
          "ConditionInfos": {
            "Conditions": []
          }
        }
      ],
      "StateConfigList": []
    },
    {
      "RegionID": 1,
      "ConnectivityList": [
        {
          "FromRegionID": 1,
          "ToRegionID": 5,
          "HasConnectWayPoint": true,
          "ConnectPointKey": "Connect_1",
          "ConditionInfos": {
            "Conditions": []
          }
        },
        {
          "FromRegionID": 1,
          "ToRegionID": 6,
          "HasConnectWayPoint": true,
          "ConnectPointKey": "Connect_2",
          "ConditionInfos": {
            "Conditions": []
          }
        }
      ],
      "StateConfigList": []
    },
    {
      "RegionID": 2,
      "ConnectivityList": [
        {
          "FromRegionID": 2,
          "ToRegionID": 4,
          "HasConnectWayPoint": true,
          "ConnectPointKey": "Connect_9",
          "ConditionInfos": {
            "Conditions": []
          }
        }
      ],
      "StateConfigList": []
    },
    {
      "RegionID": 4,
      "ConnectivityList": [
        {
          "FromRegionID": 4,
          "ToRegionID": 2,
          "HasConnectWayPoint": true,
          "ConnectPointKey": "Connect_9",
          "ConditionInfos": {
            "Conditions": []
          }
        },
        {
          "FromRegionID": 4,
          "ToRegionID": 3,
          "HasConnectWayPoint": true,
          "ConnectPointKey": "Connect_8",
          "ConditionInfos": {
            "Conditions": []
          }
        }
      ],
      "StateConfigList": []
    },
    {
      "RegionID": 6,
      "ConnectivityList": [
        {
          "FromRegionID": 6,
          "ToRegionID": 3,
          "HasConnectWayPoint": true,
          "ConnectPointKey": "Connect_3",
          "ConditionInfos": {
            "Conditions": []
          }
        },
        {
          "FromRegionID": 6,
          "ToRegionID": 1,
          "HasConnectWayPoint": true,
          "ConnectPointKey": "Connect_2",
          "ConditionInfos": {
            "Conditions": []
          }
        }
      ],
      "StateConfigList": []
    }
  ]
}