{
  "OnStartSequece": [
    {
      "TaskList": [
        {
          "$type": "RPG.GameCore.LevelPerformanceInitialize",
          "PerformanceType": "C",
          "AreaPrefabPath": "Story/Mission/1033806/Story103380612.prefab",
          "CreateCharacterList": [
            {
              "CharacterUniqueName": "Firefly_00_C00",
              "AvatarID": "NPC_Avatar_Maid_Firefly_00",
              "AreaName": "Story103380612.prefab"
            },
            {
              "CharacterUniqueName": "W3_Male_GopherWood_C00",
              "AvatarID": "NPC_Full_W3_Male_GopherWood",
              "AreaName": "Story103380612.prefab"
            },
            {
              "CharacterUniqueName": "Prop_Common_ConstanceCandle_01_C00",
              "AvatarID": "Prop_Common_ConstanceCandle_01",
              "AreaName": "Story103380612.prefab"
            }
          ],
          "CaptureNPCList": [],
          "HideNPC": true,
          "EntityVisiableList": [],
          "HideProp": true,
          "PropVisiableList": [],
          "HideLocalPlayer": true,
          "FirstCameraAnchor": "cam77b",
          "StreamingSourcesInBlackMask": [],
          "StreamingSourcesAfterBlackMask": [],
          "MarkStreamingItems": [],
          "AudioStateList": []
        },
        {
          "$type": "RPG.GameCore.PlayTimeline",
          "TimelineName": "Story/Mission/1033806/Story10338061201.playable",
          "Type": "Story"
        },
        {
          "$type": "RPG.GameCore.EndPerformance"
        }
      ]
    },
    {
      "TaskList": [
        {
          "$type": "RPG.GameCore.WaitPerformanceEnd"
        },
        {
          "$type": "RPG.GameCore.FinishLevelGraph"
        }
      ]
    }
  ],
  "Type": "PerformanceC"
}