{
  "BakeInfoLayouts": [
    {
      "UniqueName": "MAvatar_Natasha_00_HOT_HPByMaxHP",
      "Offset": 5000
    },
    {
      "UniqueName": "MAvatar_Natasha_00_Passive_FatigueRatio",
      "Offset": 5238
    },
    {
      "UniqueName": "MAvatar_Natasha_00_BPSkill_DefenceRatioUp",
      "Offset": 5340
    },
    {
      "UniqueName": "Avatar_Natasha_00_Skill01_Phase01",
      "TypeId": "TypeId_TurnBasedAbilityConfig",
      "Offset": 2
    },
    {
      "UniqueName": "Avatar_Natasha_00_Skill01_Phase02",
      "TypeId": "TypeId_TurnBasedAbilityConfig",
      "Offset": 140
    },
    {
      "UniqueName": "Avatar_Natasha_00_Skill02_Phase01",
      "TypeId": "TypeId_TurnBasedAbilityConfig",
      "Offset": 688
    },
    {
      "UniqueName": "Avatar_Natasha_00_Skill02_Phase02",
      "TypeId": "TypeId_TurnBasedAbilityConfig",
      "Offset": 954
    },
    {
      "UniqueName": "Avatar_Natasha_00_Skill03_EnterReady",
      "TypeId": "TypeId_TurnBasedAbilityConfig",
      "Offset": 1571
    },
    {
      "UniqueName": "Avatar_Natasha_00_Skill03_Phase01",
      "TypeId": "TypeId_TurnBasedAbilityConfig",
      "Offset": 1848
    },
    {
      "UniqueName": "Avatar_Natasha_00_Skill03_Phase02",
      "TypeId": "TypeId_TurnBasedAbilityConfig",
      "Offset": 2193
    },
    {
      "UniqueName": "Avatar_Natasha_00_PassiveSkill01",
      "TypeId": "TypeId_TurnBasedAbilityConfig",
      "Offset": 3066
    },
    {
      "UniqueName": "Avatar_Natasha_SkillMazeInLevel",
      "TypeId": "TypeId_TurnBasedAbilityConfig",
      "Offset": 3468
    },
    {
      "UniqueName": "Avatar_Natasha_SkillTree02",
      "TypeId": "TypeId_TurnBasedAbilityConfig",
      "Offset": 3893
    },
    {
      "UniqueName": "Avatar_Natasha_00_Rank04",
      "TypeId": "TypeId_TurnBasedAbilityConfig",
      "Offset": 3991
    },
    {
      "UniqueName": "Avatar_Natasha_00_Rank01",
      "TypeId": "TypeId_TurnBasedAbilityConfig",
      "Offset": 4209
    },
    {
      "UniqueName": "Avatar_Natasha_00_Rank01_InsertSkill_Phase01",
      "TypeId": "TypeId_TurnBasedAbilityConfig",
      "Offset": 4456
    },
    {
      "UniqueName": "Avatar_Natasha_00_Rank01_InsertSkill_Phase02",
      "TypeId": "TypeId_TurnBasedAbilityConfig",
      "Offset": 4672
    }
  ]
}