{
  "OnInitSequece": [],
  "OnStartSequece": [
    {
      "TaskList": [
        {
          "$type": "RPG.GameCore.TriggerPerformance",
          "PerformanceType": "D",
          "PerformanceID": 104366007,
          "MaskConfig": {
            "UseExcelData": false,
            "StartBlack": "NoPre",
            "EndBlack": "NoPost"
          },
          "ValueSource": {}
        },
        {
          "$type": "RPG.GameCore.SetLoadingStratageType",
          "StratageType": "Plain"
        },
        {
          "$type": "RPG.GameCore.ClientFinishMission",
          "SubmissionID": 104365104
        }
      ]
    }
  ],
  "Type": "Group"
}