[
  {
    "HeliobusSpecialPostID": 6101,
    "SubMissionID": 801510118,
    "PostImgIDList": [
      6101
    ],
    "TemplateIDList": [
      610101,
      610102,
      610103
    ],
    "Likes": [
      {
        "FGCDBGABKFG": 698
      },
      {
        "MNPBPDJJABP": 1,
        "FGCDBGABKFG": 1016
      },
      {
        "MNPBPDJJABP": 2,
        "FGCDBGABKFG": 1330
      },
      {
        "MNPBPDJJABP": 3,
        "FGCDBGABKFG": 4218
      },
      {
        "MNPBPDJJABP": 4,
        "FGCDBGABKFG": 5667
      },
      {
        "MNPBPDJJABP": 5,
        "FGCDBGABKFG": 7005
      },
      {
        "MNPBPDJJABP": 6,
        "FGCDBGABKFG": 18009
      },
      {
        "MNPBPDJJABP": 7,
        "FGCDBGABKFG": 22503
      },
      {
        "MNPBPDJJABP": 8,
        "FGCDBGABKFG": 25166
      },
      {
        "MNPBPDJJABP": 9,
        "FGCDBGABKFG": 27955
      },
      {
        "MNPBPDJJABP": 10,
        "FGCDBGABKFG": 54113
      },
      {
        "MNPBPDJJABP": 11,
        "FGCDBGABKFG": 63141
      },
      {
        "MNPBPDJJABP": 12,
        "FGCDBGABKFG": 71056
      },
      {
        "MNPBPDJJABP": 13,
        "FGCDBGABKFG": 77400
      },
      {
        "MNPBPDJJABP": 14,
        "FGCDBGABKFG": 93683
      }
    ]
  },
  {
    "HeliobusSpecialPostID": 6102,
    "SubMissionID": 801510201,
    "PostImgIDList": [
      6102
    ],
    "TemplateIDList": [
      610201,
      610202,
      610203
    ],
    "Likes": [
      {
        "FGCDBGABKFG": 4673
      },
      {
        "MNPBPDJJABP": 1,
        "FGCDBGABKFG": 6232
      },
      {
        "MNPBPDJJABP": 2,
        "FGCDBGABKFG": 7786
      },
      {
        "MNPBPDJJABP": 3,
        "FGCDBGABKFG": 19639
      },
      {
        "MNPBPDJJABP": 4,
        "FGCDBGABKFG": 24733
      },
      {
        "MNPBPDJJABP": 5,
        "FGCDBGABKFG": 27887
      },
      {
        "MNPBPDJJABP": 6,
        "FGCDBGABKFG": 30766
      },
      {
        "MNPBPDJJABP": 7,
        "FGCDBGABKFG": 59358
      },
      {
        "MNPBPDJJABP": 8,
        "FGCDBGABKFG": 68079
      },
      {
        "MNPBPDJJABP": 9,
        "FGCDBGABKFG": 76132
      },
      {
        "MNPBPDJJABP": 10,
        "FGCDBGABKFG": 83585
      },
      {
        "MNPBPDJJABP": 11,
        "FGCDBGABKFG": 100570
      },
      {
        "MNPBPDJJABP": 12,
        "FGCDBGABKFG": 100570
      },
      {
        "MNPBPDJJABP": 13,
        "FGCDBGABKFG": 100570
      },
      {
        "MNPBPDJJABP": 14,
        "FGCDBGABKFG": 100570
      }
    ]
  },
  {
    "HeliobusSpecialPostID": 6103,
    "SubMissionID": 801510317,
    "PostImgIDList": [
      6103
    ],
    "TemplateIDList": [
      610301,
      610302,
      610303
    ],
    "Likes": [
      {
        "FGCDBGABKFG": 19329
      },
      {
        "MNPBPDJJABP": 1,
        "FGCDBGABKFG": 24197
      },
      {
        "MNPBPDJJABP": 2,
        "FGCDBGABKFG": 27560
      },
      {
        "MNPBPDJJABP": 3,
        "FGCDBGABKFG": 30942
      },
      {
        "MNPBPDJJABP": 4,
        "FGCDBGABKFG": 59792
      },
      {
        "MNPBPDJJABP": 5,
        "FGCDBGABKFG": 69638
      },
      {
        "MNPBPDJJABP": 6,
        "FGCDBGABKFG": 78156
      },
      {
        "MNPBPDJJABP": 7,
        "FGCDBGABKFG": 85268
      },
      {
        "MNPBPDJJABP": 8,
        "FGCDBGABKFG": 101941
      },
      {
        "MNPBPDJJABP": 9,
        "FGCDBGABKFG": 101941
      },
      {
        "MNPBPDJJABP": 10,
        "FGCDBGABKFG": 101941
      },
      {
        "MNPBPDJJABP": 11,
        "FGCDBGABKFG": 101941
      },
      {
        "MNPBPDJJABP": 12,
        "FGCDBGABKFG": 101941
      },
      {
        "MNPBPDJJABP": 13,
        "FGCDBGABKFG": 101941
      },
      {
        "MNPBPDJJABP": 14,
        "FGCDBGABKFG": 101941
      }
    ]
  },
  {
    "HeliobusSpecialPostID": 6104,
    "SubMissionID": 801510414,
    "PostImgIDList": [
      6104
    ],
    "TemplateIDList": [
      610401,
      610402,
      610403
    ],
    "Likes": [
      {
        "FGCDBGABKFG": 27375
      },
      {
        "MNPBPDJJABP": 1,
        "FGCDBGABKFG": 30330
      },
      {
        "MNPBPDJJABP": 2,
        "FGCDBGABKFG": 57335
      },
      {
        "MNPBPDJJABP": 3,
        "FGCDBGABKFG": 66237
      },
      {
        "MNPBPDJJABP": 4,
        "FGCDBGABKFG": 73112
      },
      {
        "MNPBPDJJABP": 5,
        "FGCDBGABKFG": 73112
      },
      {
        "MNPBPDJJABP": 6,
        "FGCDBGABKFG": 73112
      },
      {
        "MNPBPDJJABP": 7,
        "FGCDBGABKFG": 73112
      },
      {
        "MNPBPDJJABP": 8,
        "FGCDBGABKFG": 73112
      },
      {
        "MNPBPDJJABP": 9,
        "FGCDBGABKFG": 73112
      },
      {
        "MNPBPDJJABP": 10,
        "FGCDBGABKFG": 73112
      },
      {
        "MNPBPDJJABP": 11,
        "FGCDBGABKFG": 73112
      },
      {
        "MNPBPDJJABP": 12,
        "FGCDBGABKFG": 73112
      },
      {
        "MNPBPDJJABP": 13,
        "FGCDBGABKFG": 73112
      },
      {
        "MNPBPDJJABP": 14,
        "FGCDBGABKFG": 73112
      }
    ]
  },
  {
    "HeliobusSpecialPostID": 6202,
    "SubMissionID": 801515205,
    "PostImgIDList": [
      6202
    ],
    "TemplateIDList": [
      620201,
      620202,
      620203
    ],
    "Likes": [
      {
        "FGCDBGABKFG": 1049
      },
      {
        "MNPBPDJJABP": 1,
        "FGCDBGABKFG": 1365
      },
      {
        "MNPBPDJJABP": 2,
        "FGCDBGABKFG": 4325
      },
      {
        "MNPBPDJJABP": 3,
        "FGCDBGABKFG": 5760
      },
      {
        "MNPBPDJJABP": 4,
        "FGCDBGABKFG": 7117
      },
      {
        "MNPBPDJJABP": 5,
        "FGCDBGABKFG": 18100
      },
      {
        "MNPBPDJJABP": 6,
        "FGCDBGABKFG": 22933
      },
      {
        "MNPBPDJJABP": 7,
        "FGCDBGABKFG": 25675
      },
      {
        "MNPBPDJJABP": 8,
        "FGCDBGABKFG": 28334
      },
      {
        "MNPBPDJJABP": 9,
        "FGCDBGABKFG": 54441
      },
      {
        "MNPBPDJJABP": 10,
        "FGCDBGABKFG": 63640
      },
      {
        "MNPBPDJJABP": 11,
        "FGCDBGABKFG": 71398
      },
      {
        "MNPBPDJJABP": 12,
        "FGCDBGABKFG": 79335
      },
      {
        "MNPBPDJJABP": 13,
        "FGCDBGABKFG": 93723
      },
      {
        "MNPBPDJJABP": 14,
        "FGCDBGABKFG": 93723
      }
    ]
  },
  {
    "HeliobusSpecialPostID": 6201,
    "SubMissionID": 801515111,
    "PostImgIDList": [
      6201
    ],
    "TemplateIDList": [
      620101,
      620102,
      620103
    ],
    "Likes": [
      {
        "FGCDBGABKFG": 1092
      },
      {
        "MNPBPDJJABP": 1,
        "FGCDBGABKFG": 1439
      },
      {
        "MNPBPDJJABP": 2,
        "FGCDBGABKFG": 4496
      },
      {
        "MNPBPDJJABP": 3,
        "FGCDBGABKFG": 6005
      },
      {
        "MNPBPDJJABP": 4,
        "FGCDBGABKFG": 7418
      },
      {
        "MNPBPDJJABP": 5,
        "FGCDBGABKFG": 19084
      },
      {
        "MNPBPDJJABP": 6,
        "FGCDBGABKFG": 24029
      },
      {
        "MNPBPDJJABP": 7,
        "FGCDBGABKFG": 27057
      },
      {
        "MNPBPDJJABP": 8,
        "FGCDBGABKFG": 30178
      },
      {
        "MNPBPDJJABP": 9,
        "FGCDBGABKFG": 57139
      },
      {
        "MNPBPDJJABP": 10,
        "FGCDBGABKFG": 67126
      },
      {
        "MNPBPDJJABP": 11,
        "FGCDBGABKFG": 74129
      },
      {
        "MNPBPDJJABP": 12,
        "FGCDBGABKFG": 82111
      },
      {
        "MNPBPDJJABP": 13,
        "FGCDBGABKFG": 98514
      },
      {
        "MNPBPDJJABP": 14,
        "FGCDBGABKFG": 98514
      }
    ]
  },
  {
    "HeliobusSpecialPostID": 6203,
    "SubMissionID": 801515311,
    "PostImgIDList": [
      6203
    ],
    "TemplateIDList": [
      620301,
      620302,
      620303
    ],
    "Likes": [
      {
        "FGCDBGABKFG": 5826
      },
      {
        "MNPBPDJJABP": 1,
        "FGCDBGABKFG": 7290
      },
      {
        "MNPBPDJJABP": 2,
        "FGCDBGABKFG": 18461
      },
      {
        "MNPBPDJJABP": 3,
        "FGCDBGABKFG": 22888
      },
      {
        "MNPBPDJJABP": 4,
        "FGCDBGABKFG": 25767
      },
      {
        "MNPBPDJJABP": 5,
        "FGCDBGABKFG": 28439
      },
      {
        "MNPBPDJJABP": 6,
        "FGCDBGABKFG": 53770
      },
      {
        "MNPBPDJJABP": 7,
        "FGCDBGABKFG": 61941
      },
      {
        "MNPBPDJJABP": 8,
        "FGCDBGABKFG": 68755
      },
      {
        "MNPBPDJJABP": 9,
        "FGCDBGABKFG": 75712
      },
      {
        "MNPBPDJJABP": 10,
        "FGCDBGABKFG": 90617
      },
      {
        "MNPBPDJJABP": 11,
        "FGCDBGABKFG": 90617
      },
      {
        "MNPBPDJJABP": 12,
        "FGCDBGABKFG": 90617
      },
      {
        "MNPBPDJJABP": 13,
        "FGCDBGABKFG": 90617
      },
      {
        "MNPBPDJJABP": 14,
        "FGCDBGABKFG": 90617
      }
    ]
  },
  {
    "HeliobusSpecialPostID": 6208,
    "SubMissionID": 801516210,
    "PostImgIDList": [
      6208
    ],
    "TemplateIDList": [
      620801,
      620802,
      620803
    ],
    "Likes": [
      {
        "FGCDBGABKFG": 7599
      },
      {
        "MNPBPDJJABP": 1,
        "FGCDBGABKFG": 9533
      },
      {
        "MNPBPDJJABP": 2,
        "FGCDBGABKFG": 24129
      },
      {
        "MNPBPDJJABP": 3,
        "FGCDBGABKFG": 30315
      },
      {
        "MNPBPDJJABP": 4,
        "FGCDBGABKFG": 34009
      },
      {
        "MNPBPDJJABP": 5,
        "FGCDBGABKFG": 37521
      },
      {
        "MNPBPDJJABP": 6,
        "FGCDBGABKFG": 71242
      },
      {
        "MNPBPDJJABP": 7,
        "FGCDBGABKFG": 81898
      },
      {
        "MNPBPDJJABP": 8,
        "FGCDBGABKFG": 90404
      },
      {
        "MNPBPDJJABP": 9,
        "FGCDBGABKFG": 98896
      },
      {
        "MNPBPDJJABP": 10,
        "FGCDBGABKFG": 118914
      },
      {
        "MNPBPDJJABP": 11,
        "FGCDBGABKFG": 118914
      },
      {
        "MNPBPDJJABP": 12,
        "FGCDBGABKFG": 118914
      },
      {
        "MNPBPDJJABP": 13,
        "FGCDBGABKFG": 118914
      },
      {
        "MNPBPDJJABP": 14,
        "FGCDBGABKFG": 118914
      }
    ]
  },
  {
    "HeliobusSpecialPostID": 6205,
    "SubMissionID": 801515705,
    "PostImgIDList": [
      6205
    ],
    "TemplateIDList": [
      620501,
      620502,
      620503
    ],
    "Likes": [
      {
        "FGCDBGABKFG": 26939
      },
      {
        "MNPBPDJJABP": 1,
        "FGCDBGABKFG": 30404
      },
      {
        "MNPBPDJJABP": 2,
        "FGCDBGABKFG": 33733
      },
      {
        "MNPBPDJJABP": 3,
        "FGCDBGABKFG": 64450
      },
      {
        "MNPBPDJJABP": 4,
        "FGCDBGABKFG": 74692
      },
      {
        "MNPBPDJJABP": 5,
        "FGCDBGABKFG": 82605
      },
      {
        "MNPBPDJJABP": 6,
        "FGCDBGABKFG": 90700
      },
      {
        "MNPBPDJJABP": 7,
        "FGCDBGABKFG": 107997
      },
      {
        "MNPBPDJJABP": 8,
        "FGCDBGABKFG": 107997
      },
      {
        "MNPBPDJJABP": 9,
        "FGCDBGABKFG": 107997
      },
      {
        "MNPBPDJJABP": 10,
        "FGCDBGABKFG": 107997
      },
      {
        "MNPBPDJJABP": 11,
        "FGCDBGABKFG": 107997
      },
      {
        "MNPBPDJJABP": 12,
        "FGCDBGABKFG": 107997
      },
      {
        "MNPBPDJJABP": 13,
        "FGCDBGABKFG": 107997
      },
      {
        "MNPBPDJJABP": 14,
        "FGCDBGABKFG": 107997
      }
    ]
  },
  {
    "HeliobusSpecialPostID": 6206,
    "SubMissionID": 801516112,
    "PostImgIDList": [
      6206
    ],
    "TemplateIDList": [
      620601,
      620602,
      620603
    ],
    "Likes": [
      {
        "FGCDBGABKFG": 25615
      },
      {
        "MNPBPDJJABP": 1,
        "FGCDBGABKFG": 29245
      },
      {
        "MNPBPDJJABP": 2,
        "FGCDBGABKFG": 32770
      },
      {
        "MNPBPDJJABP": 3,
        "FGCDBGABKFG": 63158
      },
      {
        "MNPBPDJJABP": 4,
        "FGCDBGABKFG": 72915
      },
      {
        "MNPBPDJJABP": 5,
        "FGCDBGABKFG": 81900
      },
      {
        "MNPBPDJJABP": 6,
        "FGCDBGABKFG": 91012
      },
      {
        "MNPBPDJJABP": 7,
        "FGCDBGABKFG": 108915
      },
      {
        "MNPBPDJJABP": 8,
        "FGCDBGABKFG": 108915
      },
      {
        "MNPBPDJJABP": 9,
        "FGCDBGABKFG": 108915
      },
      {
        "MNPBPDJJABP": 10,
        "FGCDBGABKFG": 108915
      },
      {
        "MNPBPDJJABP": 11,
        "FGCDBGABKFG": 108915
      },
      {
        "MNPBPDJJABP": 12,
        "FGCDBGABKFG": 108915
      },
      {
        "MNPBPDJJABP": 13,
        "FGCDBGABKFG": 108915
      },
      {
        "MNPBPDJJABP": 14,
        "FGCDBGABKFG": 108915
      }
    ]
  },
  {
    "HeliobusSpecialPostID": 6207,
    "SubMissionID": 801516324,
    "PostImgIDList": [
      6207
    ],
    "TemplateIDList": [
      620701,
      620702,
      620703
    ],
    "Likes": [
      {
        "FGCDBGABKFG": 69767
      },
      {
        "MNPBPDJJABP": 1,
        "FGCDBGABKFG": 76936
      },
      {
        "MNPBPDJJABP": 2,
        "FGCDBGABKFG": 84233
      },
      {
        "MNPBPDJJABP": 3,
        "FGCDBGABKFG": 99944
      },
      {
        "MNPBPDJJABP": 4,
        "FGCDBGABKFG": 99944
      },
      {
        "MNPBPDJJABP": 5,
        "FGCDBGABKFG": 99944
      },
      {
        "MNPBPDJJABP": 6,
        "FGCDBGABKFG": 99944
      },
      {
        "MNPBPDJJABP": 7,
        "FGCDBGABKFG": 99944
      },
      {
        "MNPBPDJJABP": 8,
        "FGCDBGABKFG": 99944
      },
      {
        "MNPBPDJJABP": 9,
        "FGCDBGABKFG": 99944
      },
      {
        "MNPBPDJJABP": 10,
        "FGCDBGABKFG": 99944
      },
      {
        "MNPBPDJJABP": 11,
        "FGCDBGABKFG": 99944
      },
      {
        "MNPBPDJJABP": 12,
        "FGCDBGABKFG": 99944
      },
      {
        "MNPBPDJJABP": 13,
        "FGCDBGABKFG": 99944
      },
      {
        "MNPBPDJJABP": 14,
        "FGCDBGABKFG": 99944
      }
    ]
  },
  {
    "HeliobusSpecialPostID": 6204,
    "SubMissionID": 801515506,
    "PostImgIDList": [
      6204
    ],
    "TemplateIDList": [
      620401,
      620402,
      620403
    ],
    "Likes": [
      {
        "FGCDBGABKFG": 73312
      },
      {
        "MNPBPDJJABP": 1,
        "FGCDBGABKFG": 76936
      },
      {
        "MNPBPDJJABP": 2,
        "FGCDBGABKFG": 84233
      },
      {
        "MNPBPDJJABP": 3,
        "FGCDBGABKFG": 99944
      },
      {
        "MNPBPDJJABP": 4,
        "FGCDBGABKFG": 99944
      },
      {
        "MNPBPDJJABP": 5,
        "FGCDBGABKFG": 99944
      },
      {
        "MNPBPDJJABP": 6,
        "FGCDBGABKFG": 99944
      },
      {
        "MNPBPDJJABP": 7,
        "FGCDBGABKFG": 99944
      },
      {
        "MNPBPDJJABP": 8,
        "FGCDBGABKFG": 99944
      },
      {
        "MNPBPDJJABP": 9,
        "FGCDBGABKFG": 99944
      },
      {
        "MNPBPDJJABP": 10,
        "FGCDBGABKFG": 99944
      },
      {
        "MNPBPDJJABP": 11,
        "FGCDBGABKFG": 99944
      },
      {
        "MNPBPDJJABP": 12,
        "FGCDBGABKFG": 99944
      },
      {
        "MNPBPDJJABP": 13,
        "FGCDBGABKFG": 99944
      },
      {
        "MNPBPDJJABP": 14,
        "FGCDBGABKFG": 99944
      }
    ]
  },
  {
    "HeliobusSpecialPostID": 6209,
    "SubMissionID": 801515313,
    "PostImgIDList": [
      6203
    ],
    "TemplateIDList": [
      620301,
      620302,
      620303
    ],
    "Likes": [
      {
        "FGCDBGABKFG": 5826
      },
      {
        "MNPBPDJJABP": 1,
        "FGCDBGABKFG": 7290
      },
      {
        "MNPBPDJJABP": 2,
        "FGCDBGABKFG": 18461
      },
      {
        "MNPBPDJJABP": 3,
        "FGCDBGABKFG": 22888
      },
      {
        "MNPBPDJJABP": 4,
        "FGCDBGABKFG": 25767
      },
      {
        "MNPBPDJJABP": 5,
        "FGCDBGABKFG": 28439
      },
      {
        "MNPBPDJJABP": 6,
        "FGCDBGABKFG": 53770
      },
      {
        "MNPBPDJJABP": 7,
        "FGCDBGABKFG": 61941
      },
      {
        "MNPBPDJJABP": 8,
        "FGCDBGABKFG": 68755
      },
      {
        "MNPBPDJJABP": 9,
        "FGCDBGABKFG": 75712
      },
      {
        "MNPBPDJJABP": 10,
        "FGCDBGABKFG": 90617
      },
      {
        "MNPBPDJJABP": 11,
        "FGCDBGABKFG": 90617
      },
      {
        "MNPBPDJJABP": 12,
        "FGCDBGABKFG": 90617
      },
      {
        "MNPBPDJJABP": 13,
        "FGCDBGABKFG": 90617
      },
      {
        "MNPBPDJJABP": 14,
        "FGCDBGABKFG": 90617
      }
    ]
  },
  {
    "HeliobusSpecialPostID": 6701,
    "SubMissionID": 801517103,
    "PostImgIDList": [
      6701
    ],
    "TemplateIDList": [
      670101
    ],
    "Likes": [
      {
        "FGCDBGABKFG": 30535
      },
      {
        "MNPBPDJJABP": 1,
        "FGCDBGABKFG": 34061
      },
      {
        "MNPBPDJJABP": 2,
        "FGCDBGABKFG": 38152
      },
      {
        "MNPBPDJJABP": 3,
        "FGCDBGABKFG": 72009
      },
      {
        "MNPBPDJJABP": 4,
        "FGCDBGABKFG": 83407
      },
      {
        "MNPBPDJJABP": 5,
        "FGCDBGABKFG": 92443
      },
      {
        "MNPBPDJJABP": 6,
        "FGCDBGABKFG": 102306
      },
      {
        "MNPBPDJJABP": 7,
        "FGCDBGABKFG": 122540
      },
      {
        "MNPBPDJJABP": 8,
        "FGCDBGABKFG": 122540
      },
      {
        "MNPBPDJJABP": 9,
        "FGCDBGABKFG": 122540
      },
      {
        "MNPBPDJJABP": 10,
        "FGCDBGABKFG": 122540
      },
      {
        "MNPBPDJJABP": 11,
        "FGCDBGABKFG": 122540
      },
      {
        "MNPBPDJJABP": 12,
        "FGCDBGABKFG": 122540
      },
      {
        "MNPBPDJJABP": 13,
        "FGCDBGABKFG": 122540
      },
      {
        "MNPBPDJJABP": 14,
        "FGCDBGABKFG": 122540
      }
    ]
  },
  {
    "HeliobusSpecialPostID": 6702,
    "SubMissionID": 801517208,
    "PostImgIDList": [
      6702
    ],
    "TemplateIDList": [
      670201
    ],
    "Likes": [
      {
        "FGCDBGABKFG": 133056
      },
      {
        "MNPBPDJJABP": 1,
        "FGCDBGABKFG": 133056
      },
      {
        "MNPBPDJJABP": 2,
        "FGCDBGABKFG": 133056
      },
      {
        "MNPBPDJJABP": 3,
        "FGCDBGABKFG": 133056
      },
      {
        "MNPBPDJJABP": 4,
        "FGCDBGABKFG": 133056
      },
      {
        "MNPBPDJJABP": 5,
        "FGCDBGABKFG": 133056
      },
      {
        "MNPBPDJJABP": 6,
        "FGCDBGABKFG": 133056
      },
      {
        "MNPBPDJJABP": 7,
        "FGCDBGABKFG": 133056
      },
      {
        "MNPBPDJJABP": 8,
        "FGCDBGABKFG": 133056
      },
      {
        "MNPBPDJJABP": 9,
        "FGCDBGABKFG": 133056
      },
      {
        "MNPBPDJJABP": 10,
        "FGCDBGABKFG": 133056
      },
      {
        "MNPBPDJJABP": 11,
        "FGCDBGABKFG": 133056
      },
      {
        "MNPBPDJJABP": 12,
        "FGCDBGABKFG": 133056
      },
      {
        "MNPBPDJJABP": 13,
        "FGCDBGABKFG": 133056
      },
      {
        "MNPBPDJJABP": 14,
        "FGCDBGABKFG": 133056
      }
    ]
  },
  {
    "HeliobusSpecialPostID": 6703,
    "SubMissionID": 801517309,
    "PostImgIDList": [
      6703
    ],
    "TemplateIDList": [
      670301
    ],
    "Likes": [
      {
        "FGCDBGABKFG": 67364
      },
      {
        "MNPBPDJJABP": 1,
        "FGCDBGABKFG": 74489
      },
      {
        "MNPBPDJJABP": 2,
        "FGCDBGABKFG": 82333
      },
      {
        "MNPBPDJJABP": 3,
        "FGCDBGABKFG": 97951
      },
      {
        "MNPBPDJJABP": 4,
        "FGCDBGABKFG": 97951
      },
      {
        "MNPBPDJJABP": 5,
        "FGCDBGABKFG": 97951
      },
      {
        "MNPBPDJJABP": 6,
        "FGCDBGABKFG": 97951
      },
      {
        "MNPBPDJJABP": 7,
        "FGCDBGABKFG": 97951
      },
      {
        "MNPBPDJJABP": 8,
        "FGCDBGABKFG": 97951
      },
      {
        "MNPBPDJJABP": 9,
        "FGCDBGABKFG": 97951
      },
      {
        "MNPBPDJJABP": 10,
        "FGCDBGABKFG": 97951
      },
      {
        "MNPBPDJJABP": 11,
        "FGCDBGABKFG": 97951
      },
      {
        "MNPBPDJJABP": 12,
        "FGCDBGABKFG": 97951
      },
      {
        "MNPBPDJJABP": 13,
        "FGCDBGABKFG": 97951
      },
      {
        "MNPBPDJJABP": 14,
        "FGCDBGABKFG": 97951
      }
    ]
  }
]