[
  {
    "DOLOCHAIFAM": 100101,
    "HJLMBALLDAO": "",
    "AMOLKBCBDGK": {
      "Hash": 6636153336510038151
    }
  },
  {
    "DOLOCHAIFAM": 100101,
    "IMOBKMFLFEK": "PS",
    "HJLMBALLDAO": "",
    "AMOLKBCBDGK": {
      "Hash": 6954355655991997614
    }
  },
  {
    "DOLOCHAIFAM": 100101,
    "IMOBKMFLFEK": "Mobile",
    "HJLMBALLDAO": "",
    "AMOLKBCBDGK": {
      "Hash": 15108953494606530625
    }
  },
  {
    "DOLOCHAIFAM": 100102,
    "HJLMBALLDAO": "",
    "AMOLKBCBDGK": {
      "Hash": 5871275187618895119
    }
  },
  {
    "DOLOCHAIFAM": 100201,
    "HJLMBALLDAO": "",
    "AMOLKBCBDGK": {
      "Hash": 17678679546149506827
    }
  },
  {
    "DOLOCHAIFAM": 100202,
    "HJLMBALLDAO": "",
    "AMOLKBCBDGK": {
      "Hash": 3539769443821247470
    }
  },
  {
    "DOLOCHAIFAM": 100301,
    "HJLMBALLDAO": "",
    "AMOLKBCBDGK": {
      "Hash": 7157329044716149787
    }
  },
  {
    "DOLOCHAIFAM": 100401,
    "HJLMBALLDAO": "",
    "AMOLKBCBDGK": {
      "Hash": 9229421694498470595
    }
  },
  {
    "DOLOCHAIFAM": 100402,
    "HJLMBALLDAO": "",
    "AMOLKBCBDGK": {
      "Hash": 10215485050145150081
    }
  },
  {
    "DOLOCHAIFAM": 100501,
    "HJLMBALLDAO": "",
    "AMOLKBCBDGK": {
      "Hash": 1873936313445032672
    }
  },
  {
    "DOLOCHAIFAM": 100502,
    "HJLMBALLDAO": "",
    "AMOLKBCBDGK": {
      "Hash": 13638103736544945882
    }
  },
  {
    "DOLOCHAIFAM": 100601,
    "HJLMBALLDAO": "SpriteOutput/TutorialPic/TutorialPage_100601_5D.png",
    "AMOLKBCBDGK": {
      "Hash": 18123174720661139407
    }
  },
  {
    "DOLOCHAIFAM": 100602,
    "HJLMBALLDAO": "SpriteOutput/TutorialPic/TutorialPage_100601_5D2.png",
    "AMOLKBCBDGK": {
      "Hash": 3024779893781758340
    }
  },
  {
    "DOLOCHAIFAM": 100701,
    "HJLMBALLDAO": "",
    "AMOLKBCBDGK": {
      "Hash": 13815985685295922217
    }
  },
  {
    "DOLOCHAIFAM": 100702,
    "HJLMBALLDAO": "",
    "AMOLKBCBDGK": {
      "Hash": 14984699016721221934
    }
  },
  {
    "DOLOCHAIFAM": 100801,
    "HJLMBALLDAO": "",
    "AMOLKBCBDGK": {
      "Hash": 7076696086189047969
    }
  },
  {
    "DOLOCHAIFAM": 100802,
    "HJLMBALLDAO": "",
    "AMOLKBCBDGK": {
      "Hash": 3244298648387949994
    }
  },
  {
    "DOLOCHAIFAM": 100901,
    "HJLMBALLDAO": "SpriteOutput/TutorialPic/TutorialPage_100901_5D.png",
    "AMOLKBCBDGK": {
      "Hash": 6960621628758807177
    }
  },
  {
    "DOLOCHAIFAM": 100902,
    "HJLMBALLDAO": "SpriteOutput/TutorialPic/TutorialPage_100901_5D2.png",
    "AMOLKBCBDGK": {
      "Hash": 3988545190137717182
    }
  },
  {
    "DOLOCHAIFAM": 100903,
    "HJLMBALLDAO": "SpriteOutput/TutorialPic/TutorialPage_100901_5D3.png",
    "AMOLKBCBDGK": {
      "Hash": 2810669666865218411
    }
  },
  {
    "DOLOCHAIFAM": 101001,
    "HJLMBALLDAO": "",
    "AMOLKBCBDGK": {
      "Hash": 3690876982495797257
    }
  },
  {
    "DOLOCHAIFAM": 101002,
    "HJLMBALLDAO": "",
    "AMOLKBCBDGK": {
      "Hash": 979459691617477416
    }
  },
  {
    "DOLOCHAIFAM": 101101,
    "HJLMBALLDAO": "SpriteOutput/TutorialPic/TutorialPage_101101_5D.png",
    "AMOLKBCBDGK": {
      "Hash": 10247660615749257899
    }
  },
  {
    "DOLOCHAIFAM": 101102,
    "HJLMBALLDAO": "SpriteOutput/TutorialPic/TutorialPage_101101_5D2.png",
    "AMOLKBCBDGK": {
      "Hash": 10986939873537588937
    }
  },
  {
    "DOLOCHAIFAM": 101201,
    "HJLMBALLDAO": "",
    "AMOLKBCBDGK": {
      "Hash": 18059277051955759378
    }
  },
  {
    "DOLOCHAIFAM": 101301,
    "HJLMBALLDAO": "",
    "AMOLKBCBDGK": {
      "Hash": 15846195890691709445
    }
  },
  {
    "DOLOCHAIFAM": 101302,
    "HJLMBALLDAO": "",
    "AMOLKBCBDGK": {
      "Hash": 14056455756910759138
    }
  },
  {
    "DOLOCHAIFAM": 101401,
    "HJLMBALLDAO": "",
    "AMOLKBCBDGK": {
      "Hash": 2635625928393885164
    }
  },
  {
    "DOLOCHAIFAM": 101501,
    "HJLMBALLDAO": "",
    "AMOLKBCBDGK": {
      "Hash": 1468129939138460852
    }
  },
  {
    "DOLOCHAIFAM": 101502,
    "HJLMBALLDAO": "",
    "AMOLKBCBDGK": {
      "Hash": 4496727126459220190
    }
  },
  {
    "DOLOCHAIFAM": 101601,
    "HJLMBALLDAO": "SpriteOutput/TutorialPic/TutorialPage_101601_5D.png",
    "AMOLKBCBDGK": {
      "Hash": 3007290513866760476
    }
  },
  {
    "DOLOCHAIFAM": 101701,
    "HJLMBALLDAO": "SpriteOutput/TutorialPic/TutorialPage_101701_5D.png",
    "AMOLKBCBDGK": {
      "Hash": 8257348454345208467
    }
  },
  {
    "DOLOCHAIFAM": 101801,
    "HJLMBALLDAO": "",
    "AMOLKBCBDGK": {
      "Hash": 5243622521376226033
    }
  },
  {
    "DOLOCHAIFAM": 101901,
    "HJLMBALLDAO": "SpriteOutput/TutorialPic/TutorialPage_101901_5D.png",
    "AMOLKBCBDGK": {
      "Hash": 5021535367345575278
    }
  },
  {
    "DOLOCHAIFAM": 102001,
    "HJLMBALLDAO": "SpriteOutput/TutorialPic/TutorialPage_102001_5D.png",
    "AMOLKBCBDGK": {
      "Hash": 9062343675992595233
    }
  },
  {
    "DOLOCHAIFAM": 102101,
    "HJLMBALLDAO": "SpriteOutput/TutorialPic/TutorialPage_102101_5D.png",
    "AMOLKBCBDGK": {
      "Hash": 87919985752505878
    }
  },
  {
    "DOLOCHAIFAM": 102201,
    "HJLMBALLDAO": "SpriteOutput/TutorialPic/TutorialPage_102201_5D.png",
    "AMOLKBCBDGK": {
      "Hash": 2974828034261574042
    }
  },
  {
    "DOLOCHAIFAM": 102301,
    "HJLMBALLDAO": "SpriteOutput/TutorialPic/TutorialPage_102301_5D.png",
    "AMOLKBCBDGK": {
      "Hash": 13731182004230834015
    }
  },
  {
    "DOLOCHAIFAM": 102401,
    "HJLMBALLDAO": "SpriteOutput/TutorialPic/TutorialPage_102401_5D.png",
    "AMOLKBCBDGK": {
      "Hash": 1835037250894880920
    }
  },
  {
    "DOLOCHAIFAM": 102402,
    "HJLMBALLDAO": "SpriteOutput/TutorialPic/TutorialPage_102401_5D.png",
    "AMOLKBCBDGK": {
      "Hash": 9596798172927717710
    }
  },
  {
    "DOLOCHAIFAM": 102501,
    "HJLMBALLDAO": "SpriteOutput/TutorialPic/TutorialPage_102501_5D.png",
    "AMOLKBCBDGK": {
      "Hash": 4803452344241863034
    }
  },
  {
    "DOLOCHAIFAM": 102502,
    "HJLMBALLDAO": "SpriteOutput/TutorialPic/TutorialPage_102501_5D.png",
    "AMOLKBCBDGK": {
      "Hash": 11634813090179251242
    }
  },
  {
    "DOLOCHAIFAM": 102601,
    "HJLMBALLDAO": "",
    "AMOLKBCBDGK": {
      "Hash": 330862223223676820
    }
  },
  {
    "DOLOCHAIFAM": 102602,
    "HJLMBALLDAO": "",
    "AMOLKBCBDGK": {
      "Hash": 15276428574425775152
    }
  },
  {
    "DOLOCHAIFAM": 102701,
    "HJLMBALLDAO": "SpriteOutput/TutorialPic/TutorialPage_637101.png",
    "AMOLKBCBDGK": {
      "Hash": 1585603186506288062
    }
  },
  {
    "DOLOCHAIFAM": 102702,
    "HJLMBALLDAO": "SpriteOutput/TutorialPic/TutorialPage_637102.png",
    "AMOLKBCBDGK": {
      "Hash": 2506787015054777164
    }
  },
  {
    "DOLOCHAIFAM": 102703,
    "HJLMBALLDAO": "SpriteOutput/TutorialPic/TutorialPage_637103.png",
    "AMOLKBCBDGK": {
      "Hash": 1109137175373107088
    }
  },
  {
    "DOLOCHAIFAM": 102801,
    "HJLMBALLDAO": "SpriteOutput/TutorialPic/TutorialPage_102801_5D.png",
    "AMOLKBCBDGK": {
      "Hash": 4324825339822966567
    }
  },
  {
    "DOLOCHAIFAM": 102901,
    "HJLMBALLDAO": "",
    "AMOLKBCBDGK": {
      "Hash": 1846024700163890907
    }
  },
  {
    "DOLOCHAIFAM": 103001,
    "HJLMBALLDAO": "",
    "AMOLKBCBDGK": {
      "Hash": 14790399420893517566
    }
  },
  {
    "DOLOCHAIFAM": 103101,
    "HJLMBALLDAO": "SpriteOutput/TutorialPic/TutorialPage_103101_5D.png",
    "AMOLKBCBDGK": {
      "Hash": 752009354381454577
    }
  },
  {
    "DOLOCHAIFAM": 103201,
    "HJLMBALLDAO": "SpriteOutput/TutorialPic/TutorialPage_103201_5D.png",
    "AMOLKBCBDGK": {
      "Hash": 3132300223589306708
    }
  },
  {
    "DOLOCHAIFAM": 103301,
    "HJLMBALLDAO": "SpriteOutput/TutorialPic/TutorialPage_103301_5D.png",
    "AMOLKBCBDGK": {
      "Hash": 16153337649050070591
    }
  },
  {
    "DOLOCHAIFAM": 103401,
    "HJLMBALLDAO": "SpriteOutput/TutorialPic/TutorialPage_103401_5D.png",
    "AMOLKBCBDGK": {
      "Hash": 6937823929891000863
    }
  },
  {
    "DOLOCHAIFAM": 103501,
    "HJLMBALLDAO": "SpriteOutput/TutorialPic/TutorialPage_103501_5D.png",
    "AMOLKBCBDGK": {
      "Hash": 12989768670568566565
    }
  },
  {
    "DOLOCHAIFAM": 103601,
    "HJLMBALLDAO": "",
    "AMOLKBCBDGK": {
      "Hash": 2784068708872580414
    }
  },
  {
    "DOLOCHAIFAM": 103901,
    "HJLMBALLDAO": "SpriteOutput/TutorialPic/TutorialPage_200601_5D.png",
    "AMOLKBCBDGK": {
      "Hash": 14664534065410042907
    }
  },
  {
    "DOLOCHAIFAM": 104001,
    "HJLMBALLDAO": "SpriteOutput/TutorialPic/TutorialPage_200701_5D.png",
    "AMOLKBCBDGK": {
      "Hash": 1839704511577953301
    }
  },
  {
    "DOLOCHAIFAM": 104101,
    "HJLMBALLDAO": "SpriteOutput/TutorialPic/TutorialPage_200801_5D.png",
    "AMOLKBCBDGK": {
      "Hash": 3768269226752923249
    }
  },
  {
    "DOLOCHAIFAM": 104201,
    "HJLMBALLDAO": "SpriteOutput/TutorialPic/TutorialPage_104201_5D2.png",
    "AMOLKBCBDGK": {
      "Hash": 6810244346324946568
    }
  },
  {
    "DOLOCHAIFAM": 104202,
    "HJLMBALLDAO": "SpriteOutput/TutorialPic/TutorialPage_104201_5D2.png",
    "AMOLKBCBDGK": {
      "Hash": 4406343334846630265
    }
  },
  {
    "DOLOCHAIFAM": 104201,
    "IMOBKMFLFEK": "PS",
    "HJLMBALLDAO": "SpriteOutput/TutorialPic/TutorialPage_104201_5D3.png",
    "AMOLKBCBDGK": {
      "Hash": 17924549951401251258
    }
  },
  {
    "DOLOCHAIFAM": 104202,
    "IMOBKMFLFEK": "PS",
    "HJLMBALLDAO": "SpriteOutput/TutorialPic/TutorialPage_104201_5D3.png",
    "AMOLKBCBDGK": {
      "Hash": 12544695342170475924
    }
  },
  {
    "DOLOCHAIFAM": 104201,
    "IMOBKMFLFEK": "Mobile",
    "HJLMBALLDAO": "SpriteOutput/TutorialPic/TutorialPage_104201_5D.png",
    "AMOLKBCBDGK": {
      "Hash": 7234786967261887035
    }
  },
  {
    "DOLOCHAIFAM": 104202,
    "IMOBKMFLFEK": "Mobile",
    "HJLMBALLDAO": "SpriteOutput/TutorialPic/TutorialPage_104201_5D.png",
    "AMOLKBCBDGK": {
      "Hash": 9063268071775370187
    }
  },
  {
    "DOLOCHAIFAM": 104301,
    "IMOBKMFLFEK": "Mobile",
    "HJLMBALLDAO": "SpriteOutput/TutorialPic/TutorialPage_104301_5D.png",
    "AMOLKBCBDGK": {
      "Hash": 10838273581324069915
    }
  },
  {
    "DOLOCHAIFAM": 104301,
    "IMOBKMFLFEK": "PS",
    "HJLMBALLDAO": "SpriteOutput/TutorialPic/TutorialPage_104301_5D3.png",
    "AMOLKBCBDGK": {
      "Hash": 11072343160598158115
    }
  },
  {
    "DOLOCHAIFAM": 104301,
    "HJLMBALLDAO": "SpriteOutput/TutorialPic/TutorialPage_104301_5D3.png",
    "AMOLKBCBDGK": {
      "Hash": 9788767839475495322
    }
  },
  {
    "DOLOCHAIFAM": 104401,
    "HJLMBALLDAO": "SpriteOutput/TutorialPic/TutorialPage_104401_5D.png",
    "AMOLKBCBDGK": {
      "Hash": 6695150735790773055
    }
  },
  {
    "DOLOCHAIFAM": 104402,
    "HJLMBALLDAO": "SpriteOutput/TutorialPic/TutorialPage_104401_5D.png",
    "AMOLKBCBDGK": {
      "Hash": 8214859609462150224
    }
  },
  {
    "DOLOCHAIFAM": 104501,
    "HJLMBALLDAO": "SpriteOutput/TutorialPic/TutorialPage_104501_5D.png",
    "AMOLKBCBDGK": {
      "Hash": 8357559590530336657
    }
  },
  {
    "DOLOCHAIFAM": 200101,
    "HJLMBALLDAO": "",
    "AMOLKBCBDGK": {
      "Hash": 2293201300701831068
    }
  },
  {
    "DOLOCHAIFAM": 200102,
    "HJLMBALLDAO": "",
    "AMOLKBCBDGK": {
      "Hash": 14605663487711746633
    }
  },
  {
    "DOLOCHAIFAM": 200103,
    "HJLMBALLDAO": "",
    "AMOLKBCBDGK": {
      "Hash": 8871977787649823663
    }
  },
  {
    "DOLOCHAIFAM": 200104,
    "HJLMBALLDAO": "",
    "AMOLKBCBDGK": {
      "Hash": 6398845055378131518
    }
  },
  {
    "DOLOCHAIFAM": 200105,
    "HJLMBALLDAO": "",
    "AMOLKBCBDGK": {
      "Hash": 4595684444047320884
    }
  },
  {
    "DOLOCHAIFAM": 200201,
    "HJLMBALLDAO": "",
    "AMOLKBCBDGK": {
      "Hash": 3495510646051445410
    }
  },
  {
    "DOLOCHAIFAM": 200202,
    "HJLMBALLDAO": "",
    "AMOLKBCBDGK": {
      "Hash": 11308380382724266124
    }
  },
  {
    "DOLOCHAIFAM": 200301,
    "HJLMBALLDAO": "",
    "AMOLKBCBDGK": {
      "Hash": 7086244219819371712
    }
  },
  {
    "DOLOCHAIFAM": 200401,
    "HJLMBALLDAO": "",
    "AMOLKBCBDGK": {
      "Hash": 12051147806521675080
    }
  },
  {
    "DOLOCHAIFAM": 200402,
    "HJLMBALLDAO": "",
    "AMOLKBCBDGK": {
      "Hash": 3952474096218237374
    }
  },
  {
    "DOLOCHAIFAM": 200501,
    "HJLMBALLDAO": "",
    "AMOLKBCBDGK": {
      "Hash": 17350713487243786680
    }
  },
  {
    "DOLOCHAIFAM": 200601,
    "HJLMBALLDAO": "",
    "AMOLKBCBDGK": {
      "Hash": 11470363766497220108
    }
  },
  {
    "DOLOCHAIFAM": 200602,
    "HJLMBALLDAO": "",
    "AMOLKBCBDGK": {
      "Hash": 6191763364703224117
    }
  },
  {
    "DOLOCHAIFAM": 200701,
    "HJLMBALLDAO": "",
    "AMOLKBCBDGK": {
      "Hash": 713081298326384002
    }
  }
]